{
  "name": "enter-your-project-name",
  "version": "1.0.0",
  "description": "Enter project description",
  "scripts": {
    "compile": "node compile.js",
    "test": "node compile.js && mocha -t 30000 -r ts-node/register test/index.ts",
    "deploy": "node deploy.js"
  },
  "dependencies": {
    "@types/mocha": "^7.0.2",
    "@types/node": "^14.0.5",
    "ethers": "^5.0.0-beta.190",
    "fs-extra": "8.1.0",
    "ganache-core": "^2.10.2",
    "mocha": "6.1.4",
    "solc": "^0.6.8",
    "ts-node": "^8.10.1",
    "typescript": "^3.9.3"
  }
}
